odoo/addons/account_invoice_mode_weekly/README.rst
odoo/addons/account_invoice_mode_weekly/__init__.py
odoo/addons/account_invoice_mode_weekly/__manifest__.py
odoo/addons/account_invoice_mode_weekly/data/ir_cron.xml
odoo/addons/account_invoice_mode_weekly/data/queue_job_data.xml
odoo/addons/account_invoice_mode_weekly/i18n/account_invoice_mode_weekly.pot
odoo/addons/account_invoice_mode_weekly/i18n/ca.po
odoo/addons/account_invoice_mode_weekly/i18n/es.po
odoo/addons/account_invoice_mode_weekly/i18n/fr.po
odoo/addons/account_invoice_mode_weekly/i18n/nl.po
odoo/addons/account_invoice_mode_weekly/models/__init__.py
odoo/addons/account_invoice_mode_weekly/models/res_company.py
odoo/addons/account_invoice_mode_weekly/models/res_config_settings.py
odoo/addons/account_invoice_mode_weekly/models/res_partner.py
odoo/addons/account_invoice_mode_weekly/models/sale_order.py
odoo/addons/account_invoice_mode_weekly/readme/CONTRIBUTORS.rst
odoo/addons/account_invoice_mode_weekly/readme/CREDITS.rst
odoo/addons/account_invoice_mode_weekly/readme/DESCRIPTION.rst
odoo/addons/account_invoice_mode_weekly/readme/INSTALL.rst
odoo/addons/account_invoice_mode_weekly/static/description/icon.png
odoo/addons/account_invoice_mode_weekly/static/description/index.html
odoo/addons/account_invoice_mode_weekly/tests/__init__.py
odoo/addons/account_invoice_mode_weekly/tests/test_invoice_mode_weekly.py
odoo/addons/account_invoice_mode_weekly/tests/test_invoice_mode_weekly_is_it_today.py
odoo/addons/account_invoice_mode_weekly/views/res_config_settings_views.xml
odoo14_addon_account_invoice_mode_weekly-14.0.1.2.0.dist-info/METADATA
odoo14_addon_account_invoice_mode_weekly-14.0.1.2.0.dist-info/WHEEL
odoo14_addon_account_invoice_mode_weekly-14.0.1.2.0.dist-info/top_level.txt
odoo14_addon_account_invoice_mode_weekly-14.0.1.2.0.dist-info/RECORD
